vprikol/__init__.py
vprikol/api.py
vprikol/main.py
vprikol/models/__init__.py
vprikol/models/ai.py
vprikol/models/base.py
vprikol/models/fraction.py
vprikol/models/internal.py
vprikol/models/player.py
vprikol/models/server.py
vprikol/models/token.py
vprikol-6.0.0.dist-info/METADATA
vprikol-6.0.0.dist-info/WHEEL
vprikol-6.0.0.dist-info/RECORD
